magic_paper/__init__.py
magic_paper/_paper.py
MagicPaper-1.1.1.dist-info/LICENSE
MagicPaper-1.1.1.dist-info/METADATA
MagicPaper-1.1.1.dist-info/WHEEL
MagicPaper-1.1.1.dist-info/top_level.txt
MagicPaper-1.1.1.dist-info/RECORD
